{"esuXgaMvFnd2B4QpXKHHFw==":"1-400x400.png","IGk2gskHpetpNYxz9fMH+A==":"2-206x206.png","C/0Vr3jVrJETYqOoeVzqVw==":"1-1-400x400.png","NTy/zJbPHRuFWUQyVFno+Q==":"1-2-400x400.png","/2B5sCUH9iV7/lpgrQrLFA==":"1-3-400x400.png","oEzuUk0Z8h889MBHbFglqQ==":"1-500x500.png","J8q0GK8Vb869xuJcfbhZlg==":"1-1-500x500.png","ksC8yDIySaU+UzbVCIcAKg==":"mbr-768x512.jpg","U/+ddMc3Mw5Yk8n8krPROA==":"mbr-1-768x512.jpg","eGV2L4hqPO3prcbxQWATiA==":"mbr-768x510.jpg","GbNpWj1vV35SrzRm1bBnHA==":"mbr-768x507.jpg","ywN+iQyOmf4ybNAzkGlyAg==":"mbr-768x457.jpg","HMz+VDHDwz7aanRw8k5P0A==":"mbr-2-768x512.jpg","qTj3xZNKK+gboJsCIbIcSw==":"mbr-768x521.jpg","4FJIn4HNypGWm86J+9vOmg==":"mbr-3-768x512.jpg","HTdK1rXkW2vNdlVmmlPuPA==":"mbr-768x426.jpg","D/JXQsaoqrHaYWPJrmkraA==":"mbr-768x576.jpg","EsfXCvijy/HFe0BlJQWIhQ==":"mbr-768x529.jpg","yfelSSxZRQL+GVMwp9nyNg==":"mbr-1101x610.jpg","oT+C+6iYJwbfaNRJeKjcpQ==":"mbr-1101x734.jpg","iahFGMKKQ0OdpkjYk9H5uw==":"mbr-1-1101x734.jpg","dtUnPJiAnkrCXONQS7Slhw==":"mbr-1101x619.jpg","xW6fHAUSRaPw7dfoJa184g==":"mbr-1489x1009.jpg","DKfoo3BaUi6vnJsFKxdCYg==":"mbr-1489x993.jpg","1weKU1wyrBXjfBOMSSGfEQ==":"mbr-1101x629.png","eBleHucxd8owAX9alTTS1g==":"mbr-1101x788.png","AFDbUcSlqfZWAdzVlfNKPg==":"mbr-1101x826.jpg","++jfQHLPoQIR6Chc9t+Eww==":"mbr-1101x643.jpg","BZm2qfCP2bGQh7Fv496FzQ==":"mbr-1920x1281.jpg","BE741py3O+tFZXP57KLnWg==":"1.png"}